setup.py
trepl/__init__.py
trepl/checkers.py
trepl.egg-info/PKG-INFO
trepl.egg-info/SOURCES.txt
trepl.egg-info/dependency_links.txt
trepl.egg-info/top_level.txt