Metadata-Version: 1.1
Name: trepl
Version: 0.1
Summary: Generic Tiered Replication implementation.
Home-page: https://github.com/chartbeat-labs/trepl
Author: Wes Chow
Author-email: wes@chartbeat.com
License: Apache
Keywords: tiered replication copysets
Platform: UNKNOWN
Classifier: Development Status :: 4 - Beta
Classifier: Intended Audience :: Developers
Classifier: Topic :: Utilities
Classifier: Programming Language :: Python
Classifier: License :: OSI Approved :: Apache Software License
